fiat_copilot/__init__.py
fiat_copilot/examples/assets/asset_reload.py
fiat_copilot/examples/assets/lightning_tuning_with_job_submission.py
fiat_copilot/examples/assets/my_assets.py
fiat_copilot/examples/assets/xgboost_test.py
fiat_copilot/examples/serving/batch.py
fiat_copilot/examples/serving/local_dev.py
fiat_copilot/examples/storage/obs_test.py
fiat_copilot/examples/storage/oss_test.py
fiat_copilot/examples/training/lightning_mnist.py
fiat_copilot/serving/__init__.py
fiat_copilot/serving/attendant.py
fiat_copilot/serving/context.py
fiat_copilot/serving/domain.py
fiat_copilot/trainer/__init__.py
fiat_copilot/trainer/hf_util.py
fiat_copilot/trainer/torch_util.py
fiat_copilot/trainer/xgboost_util.py
fiat_copilot/utils/__init__.py
fiat_copilot/utils/alioss.py
fiat_copilot/utils/config.py
fiat_copilot/utils/huaweiobs.py
fiat_copilot/utils/tencentcos.py
fiat_copilot/workflow/__init__.py
fiat_copilot/workflow/annotations.py
fiat_copilot/workflow/ray_utils.py
fiat_copilot/workflow/storage.py
fiat_copilot-0.2.0.dist-info/LICENSE
fiat_copilot-0.2.0.dist-info/WHEEL
fiat_copilot-0.2.0.dist-info/METADATA
fiat_copilot-0.2.0.dist-info/RECORD
