Metadata-Version: 2.1
Name: fiat-copilot
Version: 0.2.0
Summary: 🧑‍🚀 - Fiat Copilot is a variety of utilities to smooth your ML development workflow.
License: MIT
Author: ValerioL29
Author-email: cheng2029@foxmail.com
Requires-Python: >=3.10,<4.0
Classifier: License :: OSI Approved :: MIT License
Classifier: Programming Language :: Python :: 3
Classifier: Programming Language :: Python :: 3.10
Classifier: Programming Language :: Python :: 3.11
Requires-Dist: cos-python-sdk-v5 (>=1.9.24,<2.0.0)
Requires-Dist: dagit (>=1.3.4,<2.0.0)
Requires-Dist: dagster (>=1.3.4,<2.0.0)
Requires-Dist: esdk-obs-python (>=3.22.2,<4.0.0)
Requires-Dist: oss2 (>=2.17.0,<3.0.0)
Requires-Dist: ray[default] (>=2.4.0,<3.0.0)
Requires-Dist: xgboost (>=1.7.5,<2.0.0)
Requires-Dist: xgboost-ray (>=0.1.15,<0.2.0)
